{"paths":{},"types":[],"uuids":["41ywKJsOBHOKb/3Qi6DGP5","445lhvpO1Cz7xQoII3jlBw","55r0+axSZM2L24wLdBo7sB","64MDVRpTdBI6Kz2lOEyhgQ","6dCVKg+2xLvpaD7uHNuhxg","6eBWFz0oVHPLIGQKf/9Thu","71VhFCTINJM6/Ky3oX9nBT","73WnM0X1RDyYZgcYIqEVbu","bcOde5GitCPqjInQ3oiQtP","c66jWS6ttP5LrkqOr4g3/1","093pv5R1xB06G0ChtXwSrT","0alVGqecxGD6E68ET0gQ7S","0cbnVI7wRKlZfB3NSYROtb","10VCyq4alLiZtwBDxvDZYG","12UCPMM0FNcbsPI67OHepf","137wk2CHJO6b+ETdL2W/fr","15ZsC+rlJFQ4nudwqpC4/o","17aMe+G55DrocmHYk2c9Ph","1czSKxB9BJIqGPf8YTep9n","1c5Nk8ir9O86AcqQ4pxIL/","26NsnQ371B/7pbQV2rZdR2","268BZQOcBMT4gpIj0eX6EN","29FYIk+N1GYaeWH/q1NxQO","343NsIwYpIAoAgq+5H3Pb8","36R9lxHndFxaKPWetzpFK+","39YO0Bd+1MZ5hqQQIOrK2p","3c+i+61VNAx7VFDFMEysOS","3efNYsMexCmZjOdYArSIRd","45ASHFbQhKLonIqZ8vqILT","45Hf+mYu9AO4phXogR5zlW","494qH+OVBPoaL9DPdbG7P3","52J/YaePZLJZRYzoFkFVRf","59qpQCz8lHBo2f1Y8DdM1j","66mlo0bcNNbqpoerHs6X43","67vwOMJY9PALud2nK0gqj5","78hFzCkDhLooRdJPsxb8ya","7ePGxowu5H2KXqorMGkrMX","82sZkDJiVADagFTkB/bb1H","851NR70eRNxqejHHL78gN/","8c20Sso/ZEn7NUfNSM+EBh","8dydOQiGFFi4lBFuWeP/wa","94cJ5pNu9HW5fm58usdXYe","99nPNrRtFO6KhGsO/6MmP5","9e7Krq1WhMP4Ks35Vofd95","a1qwqx0YhOpKXr0ZcckgMp","a15MqU2FRBQofTHa2C8cwd","a6qfVxeclOz6l2J5SQmaBF","a7XqdYuYRAjJxBIjnsDHBl","a8LXPg7nRAyZmfM6HWZ18a","a8Oz9LIWxB1Kx5lIxTFDkW","a9PhbFcHlBr5zkHhElzYHw","b0DtsSz35Nqp4B8vuq/DZz","b0x/2UqC9GDozF5fs5uh1s","bbK0BZrnlP2JJcdScsx56b","c4P/0sBwFJTKu6JY+oUpF9","c4jf41fBBDZZoThgAMLm/d","cclDHcIpNIzrhujErLeFkt","d2/2hgcDZHq4PZ1Xkmn24q","d9JYA/cgBJp5EkJoOKSPjk","d9ORnsvM1Hxqai8pTQYN2k","dasOTcnKdChZPMzqCwHgHx","dcH3YGZM1AuaSfp3eNSrpl","e0F6CWTV1JC5tH6xkT59Gk","e2pRRN+HZHw4yguuY7+Wch","e8eR075lNImp5p0rHedPis","e8kLfxpNJHmqtCoRLlL2a3","e91WEmmaNIO7NHxyc4B7xl","e95qNjCklK1Ju777jf0yqo","eejmK3TyhF6LeGp9kwBpy5","efTvT3VoNERIle1Kd51w/8","f4AvK32GBO2p+Lv9TocRMV","fdk0jXsgtPH6IGpnlUWeKB"],"scenes":{"db://assets/Scene/Game.fire":7,"db://assets/Scene/Index.fire":0},"redirect":[10,0,11,0,12,0,13,0,15,0,16,0,17,0,19,0,24,0,25,0,30,0,31,0,33,0,34,0,41,0,46,0,47,0,49,0,50,0,51,0,54,0,55,0,58,0,59,0,60,0,61,0,62,0,63,0,64,0,69,0,71,0],"deps":["resources"],"packs":{"0298c26c0":[14,20,21,22,23,26,0,28,32,35,36,45,52,57,66,67,68],"0592c1fbe":[1,2,3,4,5,6,8,9],"0f3317520":[18,27,29,7,37,38,39,40,42,43,44,48,53,56,65,70]},"name":"main","importBase":"import","nativeBase":"native","debug":false,"isZip":false,"encrypted":false,"versions":{"import":["0298c26c0","9b7a0","0592c1fbe","303a3","0f3317520","1faa4"],"native":[1,"ce395",2,"4f9c3",3,"3ab03",4,"08d1e",5,"6d3cf",6,"c06a9",8,"62f55",9,"b9007"]}}